planga/__init__.py
planga/planga.py
planga-1.0.0.dist-info/METADATA
planga-1.0.0.dist-info/RECORD
planga-1.0.0.dist-info/WHEEL
planga-1.0.0.dist-info/dependency_links.txt
planga-1.0.0.dist-info/top_level.txt
